README
setup.py
bambu_mail/__init__.py
bambu_mail/models.py
bambu_mail/shortcuts.py
bambu_mail/tasks.py
bambu_mail/test_sending.py
bambu_mail/test_subscribing.py
bambu_mail/urls.py
bambu_mail/views.py
bambu_mail.egg-info/PKG-INFO
bambu_mail.egg-info/SOURCES.txt
bambu_mail.egg-info/dependency_links.txt
bambu_mail.egg-info/requires.txt
bambu_mail.egg-info/top_level.txt
bambu_mail/backends/__init__.py
bambu_mail/backends/postmark.py
bambu_mail/newsletter/__init__.py
bambu_mail/newsletter/mailchimp.py
bambu_mail/templates/mail/base.html
bambu_mail/templates/mail/base.txt
bambu_mail/templates/mail/footer.inc.txt
bambu_mail/templates/mail/header.inc.html
bambu_mail/templates/mail/test.txt