Metadata-Version: 1.1
Name: bambu-mail
Version: 3.2
Summary: A shortcut function for sending template-based emails in HTML and plain-text format
Home-page: https://github.com/iamsteadman/bambu-mail
Author: Steadman
Author-email: mark@steadman.io
License: UNKNOWN
Platform: UNKNOWN
Classifier: Development Status :: 4 - Beta
Classifier: Environment :: Web Environment
Classifier: Framework :: Django
